Data_Path.v
`timescale 1ns / 1ps
//////////////////////////////////////////////////////////////////////////////////
// Company: 
// Engineer: 
// 
// Create Date: 09/12/2026 10:12:07 AM
// Design Name: 
// Module Name: Data_Path
// Project Name: 
// Target Devices: 
// Tool Versions: 
// Description: 
// 
// Dependencies: 
// 
// Revision:
// Revision 0.01 - File Created
// Additional Comments:
// 
//////////////////////////////////////////////////////////////////////////////////


module Data_Path(
    input signed [15:0]  data_in,
    input la,lq,lm,clra,clrq,clrm,clrq_1,Ashift,as,clk,cnt_clr,decc,sela,selq,lq_1,
    output [1:0]q_out,
    output count_out,
    output signed [31:0]  product
);
    wire signed [15:0] x,z,q,m;
    wire q_1;
    wire [32:0] shift_out;
    wire [4:0] count;
    data_handle A (.load(la), .clr(clra), .clk(clk), .sel(sela), .data0(z), .data1(shift_out[32:17]), .data_out(x));
    PIPO M (.load(lm), .clr(clrm), .clk(clk), .data(data_in), .out(m));
    data_handle Q (.load(lq), .clr(clrq), .clk(clk), .sel(selq), .data0(data_in), .data1(shift_out[16:1]), .data_out(q));
    D_ff DFF (.clr(clrq_1), .clk(clk), .load(lq_1), .data(shift_out[0]), .out(q_1));
    shift S (.A(x), .Q(q), .Q_1(q_1), .arsht(Ashift), .out(shift_out));
    counter Counter (.clr(cnt_clr), .dec(decc), .clk(clk), .out(count));
    add_sub ASU (.a_s(as), .a(x), .b(m), .out(z));
    assign q_out={q[0],q_1};
    assign product = $signed ({x,q});
    assign count_out=~|count;
endmodule

module data_handle(
    input load,clr,clk,sel,
    input signed [15:0] data1,data0,
    output reg signed [15:0] data_out
);
    always @(posedge clk)
    begin
        if(clr)
            data_out<=16'b0;
        else if(load)
            data_out<=sel?data1:data0;

    end
endmodule

module PIPO (
    input signed [15:0] data,
    input clk,clr,load,
    output reg signed[15:0] out
);
    always @(posedge clk) 
    begin
        if(clr)
            out<=16'b0;
        else if (load)
            out<=data;
    end
endmodule

module add_sub(
    input a_s,
    input signed [15:0] a,b,
    output reg signed [15:0] out
);
    always @(*)
    begin
        if(a_s)
            out=a+b;
        else if(~a_s)
            out=a-b;
    end
endmodule

module D_ff(
    input clr,clk,data,load,
    output reg out
);
    always @(posedge clk) 
    begin
        if (clr)
            out<=1'b0;
        else if (load)
            out<=data;
    end
endmodule

module shift (
    input signed [15:0] A,Q,
    input Q_1,arsht,
    output reg signed [32:0] out
);
    always @(*)
    begin
        if(arsht)
        begin
            out= $signed ({A,Q,Q_1})>>>1;
        end
        else
            out= $signed({A,Q,Q_1});
    end
endmodule

module counter(
    input clr,dec,clk,
    output reg [4:0] out
);
    always @(posedge clk)
    begin
        if(clr)
            out<=5'b10000;
        else if(dec && out != 5'b00000)
            out<=out-5'b00001; 
    end
endmodule

Control_Path.v
`timescale 1ns / 1ps

module Control_Path(
    input clk,count_out,reset,
    input [1:0] q_out,
    output reg sela,la,clra,selq,lq,clrq,clrq_1,ashift,as,lm,clrm,clrc,decc,done,lq_1
);
    reg[2:0] state;
    localparam s0 = 3'b000 ;
    localparam s1 = 3'b001 ;
    localparam s2 = 3'b010 ;
    localparam s3 = 3'b011 ;
    localparam s4 = 3'b100 ;
    localparam s5 = 3'b101 ;
    localparam s6 = 3'b110 ;

   always @(posedge clk) begin

        if(reset)
            state<=s0;
        else
            begin
                case (state)
                    s0: state<=s1;
                    s1: state<=s2;
                    s2: 
                        begin
                            if(q_out==2'b01)
                                state<=s3;
                            else if(q_out==2'b10)
                                state<=s4;
                            else if(q_out==2'b00||q_out==2'b11)
                                state<=s5;
                        end 
                    s3: state<=s5;
                    s4: state<=s5;
                    s5: 
                        begin
                            if(count_out==1'b1) 
                                state<=s6;
                            else if(q_out==2'b10 && count_out==1'b0)
                                state<=s4;
                            else if(q_out==2'b01 && count_out==1'b0)
                                state<=s3;
                            else
                                state<=s5;
                        end
                    s6: state<=s6;
                    default: state<=s0;
                endcase
            end
    end

    always @(*) begin
            sela=0;
            la=0;
            clra=0;

            selq=0;
            lq=0;
            clrq=0;

            lq_1=0;
            clrq_1=0;

            ashift=0;
            as=0;

            lm=0;
            clrm=0;

            clrc=0;
            decc=0;

            done=0;
            case (state)
                s0:
                    begin
                        clrm=1;
                    end 
                s1:
                    begin
                        lm=1;
                        clra=1;
                        clrq=1;
                        clrq_1=1;
                        clrc=1;
                    end
                s2:
                    begin
                        selq=0;
                        lq=1;
                    end
                s3:
                    begin
                        as=1;
                        sela=0;
                        la=1;
                    end
                s4:
                    begin
                        la=1;
                    end
                s5:
                    begin
                        ashift=1;
                        decc=1;
                        sela=1;
                        la=1;
                        selq=1;
                        lq=1;
                        lq_1=1;
                    end
                s6:
                    begin
                        done=1;     
                    end
                default: 
                    begin

                    end
            endcase 
            
    end
endmodule

Booth_multi.v
module Booth_multi(
    input clk,rst,
    input [15:0] data_in,
    output [31:0] data_out,
    output done
);
    wire law,lqw,lmw,clraw,clrqw,clrmw,clrq_1w,Ashiftw,asw,cnt_clrw,deccw,selaw,selqw,lq_1w,cw;
    wire [1:0] qw;
    Control_Path CP(
        .reset(rst),
        .clk(clk),

        .count_out(cw),
        .q_out(qw),

        .sela(selaw),
        .la(law),
        .clra(clraw),

        .selq(selqw),
        .lq(lqw),
        .clrq(clrqw),

        .lq_1(lq_1w),
        .clrq_1(clrq_1w),
        
        .ashift(Ashiftw),

        .as(asw),
        
        .lm(lmw),
        .clrm(clrmw),
        .clrc(cnt_clrw),
        .decc(deccw),
        .done(done)

    );
    Data_Path DP (
        .data_in(data_in),

        .la(law),
        .lq(lqw),
        .lm(lmw),

        .clra(clraw),
        .clrq(clrqw),
        .clrm(clrmw),
        .clrq_1(clrq_1w),

        .Ashift(Ashiftw),
        .as(asw),

        .clk(clk),
        .cnt_clr(cnt_clrw),
        .decc(deccw),

        .sela(selaw),
        .selq(selqw),
        .lq_1(lq_1w),

        .q_out(qw),
        .count_out(cw),
        .product(data_out)
    );
endmodule

BM_tb.v
`timescale 1ns / 1ps

module Booth_multi_tb;

    reg clk;
    reg rst;
    reg signed [15:0] data_in;

    wire signed [31:0] data_out;
    wire done;

    Booth_multi DUT (
        .clk(clk),
        .rst(rst),
        .data_in(data_in),
        .data_out(data_out),
        .done(done)
    );

    // Clock
    initial begin
        clk = 0;
        forever #5 clk = ~clk;
    end

    // Test
    initial begin
        rst = 1;
        data_in = 16'd0;

        // Reset
        #12;
        rst = 0;

        // First input = multiplicand
        @(negedge clk);
        data_in = -16'd9;

        // Second input = multiplier
        @(negedge clk);
        data_in = 16'd9;

        // Wait for completion
        wait(done == 1);

        #2;

        $display("--------------------------------");
        $display("A       = %d", -9);
        $display("B       = %d", 9);
        $display("Product = %d", $signed(data_out));
        $display("--------------------------------");

        #10;
        $finish;
    end

    // Waveform
    initial begin
        $dumpfile("booth.vcd");
        $dumpvars(0, Booth_multi_tb);
    end

endmodule

booth.vcd
$date
	Sat Sep 12 16:24:24 2026
$end
$version
	Icarus Verilog
$end
$timescale
	1ps
$end
$scope module Booth_multi_tb $end
$var wire 1 ! done $end
$var wire 32 " data_out [31:0] $end
$var reg 1 # clk $end
$var reg 16 $ data_in [15:0] $end
$var reg 1 % rst $end
$scope module DUT $end
$var wire 1 # clk $end
$var wire 16 & data_in [15:0] $end
$var wire 1 % rst $end
$var wire 1 ' selqw $end
$var wire 1 ( selaw $end
$var wire 2 ) qw [1:0] $end
$var wire 1 * lqw $end
$var wire 1 + lq_1w $end
$var wire 1 , lmw $end
$var wire 1 - law $end
$var wire 1 ! done $end
$var wire 1 . deccw $end
$var wire 32 / data_out [31:0] $end
$var wire 1 0 cw $end
$var wire 1 1 cnt_clrw $end
$var wire 1 2 clrqw $end
$var wire 1 3 clrq_1w $end
$var wire 1 4 clrmw $end
$var wire 1 5 clraw $end
$var wire 1 6 asw $end
$var wire 1 7 Ashiftw $end
$scope module CP $end
$var wire 1 # clk $end
$var wire 1 % reset $end
$var wire 2 8 q_out [1:0] $end
$var wire 1 0 count_out $end
$var parameter 3 9 s0 $end
$var parameter 3 : s1 $end
$var parameter 3 ; s2 $end
$var parameter 3 < s3 $end
$var parameter 3 = s4 $end
$var parameter 3 > s5 $end
$var parameter 3 ? s6 $end
$var reg 1 6 as $end
$var reg 1 7 ashift $end
$var reg 1 5 clra $end
$var reg 1 1 clrc $end
$var reg 1 4 clrm $end
$var reg 1 2 clrq $end
$var reg 1 3 clrq_1 $end
$var reg 1 . decc $end
$var reg 1 ! done $end
$var reg 1 - la $end
$var reg 1 , lm $end
$var reg 1 * lq $end
$var reg 1 + lq_1 $end
$var reg 1 ( sela $end
$var reg 1 ' selq $end
$var reg 3 @ state [2:0] $end
$upscope $end
$scope module DP $end
$var wire 1 7 Ashift $end
$var wire 1 6 as $end
$var wire 1 # clk $end
$var wire 1 5 clra $end
$var wire 1 4 clrm $end
$var wire 1 2 clrq $end
$var wire 1 3 clrq_1 $end
$var wire 1 1 cnt_clr $end
$var wire 16 A data_in [15:0] $end
$var wire 1 . decc $end
$var wire 1 - la $end
$var wire 1 , lm $end
$var wire 1 * lq $end
$var wire 1 + lq_1 $end
$var wire 1 ( sela $end
$var wire 1 ' selq $end
$var wire 16 B z [15:0] $end
$var wire 16 C x [15:0] $end
$var wire 33 D shift_out [32:0] $end
$var wire 2 E q_out [1:0] $end
$var wire 1 F q_1 $end
$var wire 16 G q [15:0] $end
$var wire 32 H product [31:0] $end
$var wire 16 I m [15:0] $end
$var wire 1 0 count_out $end
$var wire 5 J count [4:0] $end
$scope module A $end
$var wire 1 # clk $end
$var wire 1 5 clr $end
$var wire 16 K data1 [15:0] $end
$var wire 1 - load $end
$var wire 1 ( sel $end
$var wire 16 L data0 [15:0] $end
$var reg 16 M data_out [15:0] $end
$upscope $end
$scope module ASU $end
$var wire 16 N a [15:0] $end
$var wire 1 6 a_s $end
$var wire 16 O b [15:0] $end
$var reg 16 P out [15:0] $end
$upscope $end
$scope module Counter $end
$var wire 1 # clk $end
$var wire 1 1 clr $end
$var wire 1 . dec $end
$var reg 5 Q out [4:0] $end
$upscope $end
$scope module DFF $end
$var wire 1 # clk $end
$var wire 1 3 clr $end
$var wire 1 R data $end
$var wire 1 + load $end
$var reg 1 F out $end
$upscope $end
$scope module M $end
$var wire 1 # clk $end
$var wire 1 4 clr $end
$var wire 16 S data [15:0] $end
$var wire 1 , load $end
$var reg 16 T out [15:0] $end
$upscope $end
$scope module Q $end
$var wire 1 # clk $end
$var wire 1 2 clr $end
$var wire 16 U data0 [15:0] $end
$var wire 16 V data1 [15:0] $end
$var wire 1 * load $end
$var wire 1 ' sel $end
$var reg 16 W data_out [15:0] $end
$upscope $end
$scope module S $end
$var wire 16 X A [15:0] $end
$var wire 16 Y Q [15:0] $end
$var wire 1 F Q_1 $end
$var wire 1 7 arsht $end
$var reg 33 Z out [32:0] $end
$upscope $end
$upscope $end
$upscope $end
$upscope $end
$enddefinitions $end
$comment Show the parameter values. $end
$dumpall
b110 ?
b101 >
b100 =
b11 <
b10 ;
b1 :
b0 9
$end
#0
$dumpvars
bx Z
bx Y
bx X
bx W
bx V
b0 U
bx T
b0 S
xR
bx Q
bx P
bx O
bx N
bx M
bx L
bx K
bx J
bx I
bx H
bx G
xF
bx E
bx D
bx C
bx B
b0 A
bx @
bx 8
x7
x6
x5
x4
x3
x2
x1
x0
bx /
x.
x-
x,
x+
x*
bx )
x(
x'
b0 &
1%
b0 $
0#
bx "
x!
$end
#5000
0!
0.
01
14
0,
06
07
03
0+
02
0*
0'
05
0-
0(
b0 @
1#
#10000
0#
#12000
0%
#15000
11
13
12
15
1,
04
b0 I
b0 O
b0 T
b1 @
1#
#20000
b1111111111110111 $
b1111111111110111 &
b1111111111110111 A
b1111111111110111 S
b1111111111110111 U
0#
#25000
0R
b0 V
b0 K
1*
01
0,
03
02
05
b1001 B
b1001 L
b1001 P
b0 D
b0 Z
b10 @
b0 C
b0 M
b0 N
b0 X
b1111111111110111 I
b1111111111110111 O
b1111111111110111 T
b0 "
b0 /
b0 H
b0 G
b0 W
b0 Y
b0 )
b0 8
b0 E
0F
00
b10000 J
b10000 Q
1#
#30000
b1001 $
b1001 &
b1001 A
b1001 S
b1001 U
0#
#35000
1R
b100 V
b1001 D
b1001 Z
b10 )
b10 8
b10 E
1+
1'
1-
1(
1.
17
1*
b1001 "
b1001 /
b1001 H
b1001 G
b1001 W
b1001 Y
b101 @
1#
#40000
0#
#45000
1R
b100 V
0.
07
0+
0*
0'
1-
0(
b1001 D
b1001 Z
b100 @
b100 "
b100 /
b100 H
b100 G
b100 W
b100 Y
b1 )
b1 8
b1 E
1F
b1111 J
b1111 Q
1#
#50000
0#
#55000
0R
b1000000000000010 V
b100 K
b10010 B
b10010 L
b10010 P
b10010000000000000100 D
b10010000000000000100 Z
1+
1*
1'
1(
1.
17
1-
b10010000000000000100 "
b10010000000000000100 /
b10010000000000000100 H
b1001 C
b1001 M
b1001 N
b1001 X
b101 @
1#
#60000
0#
#65000
b1000000000000010 V
b100 K
16
0.
07
0+
0*
0'
1-
0(
b1111111111111011 B
b1111111111111011 L
b1111111111111011 P
b10010000000000000100 D
b10010000000000000100 Z
b11 @
b100 C
b100 M
b100 N
b100 X
b1001000000000000010 "
b1001000000000000010 /
b1001000000000000010 H
b1000000000000010 G
b1000000000000010 W
b1000000000000010 Y
b0 )
b0 8
b0 E
0F
b1110 J
b1110 Q
1#
#70000
0#
#75000
b1100000000000001 V
b1111111111111101 K
b100 B
b100 L
b100 P
b111111111111110111000000000000010 D
b111111111111110111000000000000010 Z
1+
1*
1'
1(
1.
17
06
1-
b11111111111110111000000000000010 "
b11111111111110111000000000000010 /
b11111111111110111000000000000010 H
b1111111111111011 C
b1111111111111011 M
b1111111111111011 N
b1111111111111011 X
b101 @
1#
#80000
0#
#85000
1R
b1110000000000000 V
b1111111111111110 K
b110 B
b110 L
b110 P
b111111111111111011100000000000001 D
b111111111111111011100000000000001 Z
b10 )
b10 8
b10 E
b1111111111111101 C
b1111111111111101 M
b1111111111111101 N
b1111111111111101 X
b11111111111111011100000000000001 "
b11111111111111011100000000000001 /
b11111111111111011100000000000001 H
b1100000000000001 G
b1100000000000001 W
b1100000000000001 Y
b1101 J
b1101 Q
1#
#90000
0#
#95000
b111 B
b111 L
b111 P
0.
07
0+
0*
0'
1-
0(
b1100 J
b1100 Q
b1 )
b1 8
b1 E
1F
b1110000000000000 G
b1110000000000000 W
b1110000000000000 Y
b11111111111111101110000000000000 "
b11111111111111101110000000000000 /
b11111111111111101110000000000000 H
b1111111111111110 C
b1111111111111110 M
b1111111111111110 N
b1111111111111110 X
b100 @
1#
#100000
0#
#105000
0R
b1111000000000000 V
b11 K
1+
1*
1'
1(
1.
17
1-
b10000 B
b10000 L
b10000 P
b1111110000000000000 D
b1111110000000000000 Z
b101 @
b1111110000000000000 "
b1111110000000000000 /
b1111110000000000000 H
b111 C
b111 M
b111 N
b111 X
1#
#110000
0#
#115000
b1111111111111010 B
b1111111111111010 L
b1111111111111010 P
16
0.
07
0+
0*
0'
1-
0(
b1011 J
b1011 Q
b0 )
b0 8
b0 E
0F
b1111000000000000 G
b1111000000000000 W
b1111000000000000 Y
b111111000000000000 "
b111111000000000000 /
b111111000000000000 H
b11 C
b11 M
b11 N
b11 X
b11 @
1#
#120000
0#
#125000
b111100000000000 V
b1111111111111101 K
1+
1*
1'
1(
1.
17
06
1-
b11 B
b11 L
b11 P
b111111111111110101111000000000000 D
b111111111111110101111000000000000 Z
b101 @
b11111111111110101111000000000000 "
b11111111111110101111000000000000 /
b11111111111110101111000000000000 H
b1111111111111010 C
b1111111111111010 M
b1111111111111010 N
b1111111111111010 X
1#
#130000
0#
#135000
b1011110000000000 V
b1111111111111110 K
b110 B
b110 L
b110 P
b111111111111111010111100000000000 D
b111111111111111010111100000000000 Z
b1010 J
b1010 Q
b111100000000000 G
b111100000000000 W
b111100000000000 Y
b11111111111111010111100000000000 "
b11111111111111010111100000000000 /
b11111111111111010111100000000000 H
b1111111111111101 C
b1111111111111101 M
b1111111111111101 N
b1111111111111101 X
1#
#140000
0#
#145000
b101111000000000 V
b1111111111111111 K
b111 B
b111 L
b111 P
b111111111111111101011110000000000 D
b111111111111111101011110000000000 Z
b1111111111111110 C
b1111111111111110 M
b1111111111111110 N
b1111111111111110 X
b11111111111111101011110000000000 "
b11111111111111101011110000000000 /
b11111111111111101011110000000000 H
b1011110000000000 G
b1011110000000000 W
b1011110000000000 Y
b1001 J
b1001 Q
1#
#150000
0#
#155000
b1010111100000000 V
b1000 B
b1000 L
b1000 P
b111111111111111110101111000000000 D
b111111111111111110101111000000000 Z
b1000 J
b1000 Q
b101111000000000 G
b101111000000000 W
b101111000000000 Y
b11111111111111110101111000000000 "
b11111111111111110101111000000000 /
b11111111111111110101111000000000 H
b1111111111111111 C
b1111111111111111 M
b1111111111111111 N
b1111111111111111 X
1#
#160000
0#
#165000
b1101011110000000 V
b111111111111111111010111100000000 D
b111111111111111111010111100000000 Z
b11111111111111111010111100000000 "
b11111111111111111010111100000000 /
b11111111111111111010111100000000 H
b1010111100000000 G
b1010111100000000 W
b1010111100000000 Y
b111 J
b111 Q
1#
#170000
0#
#175000
b1110101111000000 V
b111111111111111111101011110000000 D
b111111111111111111101011110000000 Z
b110 J
b110 Q
b11111111111111111101011110000000 "
b11111111111111111101011110000000 /
b11111111111111111101011110000000 H
b1101011110000000 G
b1101011110000000 W
b1101011110000000 Y
1#
#180000
0#
#185000
b1111010111100000 V
b111111111111111111110101111000000 D
b111111111111111111110101111000000 Z
b11111111111111111110101111000000 "
b11111111111111111110101111000000 /
b11111111111111111110101111000000 H
b1110101111000000 G
b1110101111000000 W
b1110101111000000 Y
b101 J
b101 Q
1#
#190000
0#
#195000
b1111101011110000 V
b111111111111111111111010111100000 D
b111111111111111111111010111100000 Z
b100 J
b100 Q
b11111111111111111111010111100000 "
b11111111111111111111010111100000 /
b11111111111111111111010111100000 H
b1111010111100000 G
b1111010111100000 W
b1111010111100000 Y
1#
#200000
0#
#205000
b1111110101111000 V
b111111111111111111111101011110000 D
b111111111111111111111101011110000 Z
b11111111111111111111101011110000 "
b11111111111111111111101011110000 /
b11111111111111111111101011110000 H
b1111101011110000 G
b1111101011110000 W
b1111101011110000 Y
b11 J
b11 Q
1#
#210000
0#
#215000
b1111111010111100 V
b111111111111111111111110101111000 D
b111111111111111111111110101111000 Z
b10 J
b10 Q
b11111111111111111111110101111000 "
b11111111111111111111110101111000 /
b11111111111111111111110101111000 H
b1111110101111000 G
b1111110101111000 W
b1111110101111000 Y
1#
#220000
0#
#225000
b1111111101011110 V
b111111111111111111111111010111100 D
b111111111111111111111111010111100 Z
b11111111111111111111111010111100 "
b11111111111111111111111010111100 /
b11111111111111111111111010111100 H
b1111111010111100 G
b1111111010111100 W
b1111111010111100 Y
b1 J
b1 Q
1#
#230000
0#
#235000
b1111111110101111 V
b111111111111111111111111101011110 D
b111111111111111111111111101011110 Z
10
b0 J
b0 Q
b11111111111111111111111101011110 "
b11111111111111111111111101011110 /
b11111111111111111111111101011110 H
b1111111101011110 G
b1111111101011110 W
b1111111101011110 Y
1#
#240000
0#
#245000
0R
b1111111110101111 V
1!
0.
07
0+
0*
0'
0-
0(
b111111111111111111111111101011110 D
b111111111111111111111111101011110 Z
b10 )
b10 8
b10 E
b110 @
b11111111111111111111111110101111 "
b11111111111111111111111110101111 /
b11111111111111111111111110101111 H
b1111111110101111 G
b1111111110101111 W
b1111111110101111 Y
1#
